<annotation>
	<folder>raw_jpgs</folder>
	<filename>cards-[D9]-001.jpg</filename>
	<path>/home/avram/grad-school/hackathon_2019/app/training_data/raw_jpgs/cards-[D9]-001.jpg</path>
	<source>
		<database>Unknown</database>
	</source>
	<size>
		<width>4128</width>
		<height>2322</height>
		<depth>3</depth>
	</size>
	<segmented>0</segmented>
	<object>
		<name>default</name>
		<pose>Unspecified</pose>
		<truncated>0</truncated>
		<difficult>0</difficult>
		<bndbox>
			<xmin>1676</xmin>
			<ymin>1309</ymin>
			<xmax>2037</xmax>
			<ymax>1446</ymax>
		</bndbox>
	</object>
	<object>
		<name>default</name>
		<pose>Unspecified</pose>
		<truncated>0</truncated>
		<difficult>0</difficult>
		<bndbox>
			<xmin>2755</xmin>
			<ymin>394</ymin>
			<xmax>3112</xmax>
			<ymax>521</ymax>
		</bndbox>
	</object>
</annotation>
