<annotation>
	<folder>raw_jpgs</folder>
	<filename>cards-[DQ]-003.jpg</filename>
	<path>/home/avram/grad-school/hackathon_2019/app/training_data/raw_jpgs/cards-[DQ]-003.jpg</path>
	<source>
		<database>Unknown</database>
	</source>
	<size>
		<width>4128</width>
		<height>2322</height>
		<depth>3</depth>
	</size>
	<segmented>0</segmented>
	<object>
		<name>default</name>
		<pose>Unspecified</pose>
		<truncated>0</truncated>
		<difficult>0</difficult>
		<bndbox>
			<xmin>1479</xmin>
			<ymin>612</ymin>
			<xmax>1606</xmax>
			<ymax>933</ymax>
		</bndbox>
	</object>
	<object>
		<name>default</name>
		<pose>Unspecified</pose>
		<truncated>0</truncated>
		<difficult>0</difficult>
		<bndbox>
			<xmin>2282</xmin>
			<ymin>1618</ymin>
			<xmax>2412</xmax>
			<ymax>1921</ymax>
		</bndbox>
	</object>
</annotation>
